{
  "name": "animated-beam-curved-demo",
  "type": "registry:example",
  "dependencies": [
    "lucide-react"
  ],
  "registryDependencies": [
    "animated-beam"
  ],
  "files": [
    {
      "path": "examples/animated-beam-curved-demo.tsx",
      "content": "import { AnimatedBeam, BeamContainer, BeamNode } from \"@/registry/default/ui/animated-beam\";\nimport { Circle, Square } from \"lucide-react\";\nimport React from \"react\";\n\nexport default function AnimatedBeamCurvedDemo() {\n  const containerRef = React.useRef<HTMLDivElement>(null);\n  const fromRef = React.useRef<HTMLDivElement>(null);\n  const toRef = React.useRef<HTMLDivElement>(null);\n\n  return (\n    <BeamContainer\n      ref={containerRef}\n      className=\"mx-auto w-full flex items-center min-h-screen justify-between rounded-xl p-8\"\n    >\n      <BeamNode ref={fromRef} className=\"h-14 w-14\">\n        <Circle className=\"h-6 w-6 text-muted-foreground\" />\n      </BeamNode>\n\n      <BeamNode ref={toRef} className=\"h-14 w-14\">\n        <Square className=\"h-6 w-6 text-muted-foreground\" />\n      </BeamNode>\n\n      <AnimatedBeam\n        containerRef={containerRef}\n        fromRef={fromRef}\n        toRef={toRef}\n        curvature={0.5}\n        gradientStartColor=\"#3b82f6\"\n        gradientStopColor=\"#1d4ed8\"\n      />\n    </BeamContainer>\n  );\n}",
      "type": "registry:example",
      "target": ""
    }
  ]
}